{
    "name": "triple_shot",
    "components": {
        "ProjectileTag": { "target": "both" },
        "TransformComponent": {
            "target": "both",
            "position": { "x": 0.0, "y": 0.0 },
            "scale": { "x": 0.5, "y": 0.5 },
            "rotation": 0.0
        },
        "VelocityComponent": { "target": "both" },
        "SpriteComponent": {
            "target": "client",
            "filePath": "assets/sprites/projectile_triple.png"
        },
        "ColliderComponent": {
            "target": "both",
            "size": { "x": 12.0, "y": 12.0 }
        }
    }
}
